msservice_advisor/__init__.py
msservice_advisor/__main__.py
msservice_advisor/profiling_analyze/__init__.py
msservice_advisor/profiling_analyze/base_analyze.py
msservice_advisor/profiling_analyze/batch_analyze.py
msservice_advisor/profiling_analyze/register.py
msservice_advisor/profiling_analyze/utils.py
msservice_advisor-0.0.1a7.dist-info/METADATA
msservice_advisor-0.0.1a7.dist-info/WHEEL
msservice_advisor-0.0.1a7.dist-info/entry_points.txt
msservice_advisor-0.0.1a7.dist-info/top_level.txt
msservice_advisor-0.0.1a7.dist-info/RECORD
