Metadata-Version: 2.1
Name: msservice-advisor
Version: 0.0.1a7
Summary: MindStudio Service Profiler Advisor
License: Apache-2.0
Project-URL: source, https://gitee.com/ascend/msit/tree/msserviceprofiler_dev/msservice_advisor
Project-URL: documentation, https://gitee.com/ascend/msit/tree/msserviceprofiler_dev/msservice_advisor
Project-URL: tracker, https://gitee.com/ascend/msit/issues
Keywords: msservice,advisor
Classifier: Programming Language :: Python :: 3
Classifier: Programming Language :: Python :: 3.8
Classifier: Programming Language :: Python :: 3.9
Classifier: Programming Language :: Python :: 3.10
Classifier: Programming Language :: Python :: 3.11
Classifier: License :: OSI Approved :: Apache Software License
Classifier: Operating System :: OS Independent
Requires-Python: >=3.8
Requires-Dist: scipy
